{
  "表情":{
    "SUBCLASS_OF":[
      "1.乐",
      "2,好",
      "3,怒",
      "4,哀",
      "5,惧",
      "6,恶",
      "7,惊"
    ]
  },
  "乐":{
    "SUBCLASS_OF":[
      "1.快乐",
      "2.安心"
    ]
  },
  "好":{
    "SUBCLASS_OF":[
      "1.尊敬",
      "2.赞扬",
      "3.相信",
      "4.喜爱",
      "5.祝愿"
    ]
  },
  "怒":{
    "SUBCLASS_OF":[
      "1.愤怒"
    ]
  },
  "哀":{
    "SUBCLASS_OF":[
      "1.悲伤",
      "2.失望",
      "3.疚",
      "4.思",
      "5.慌"
    ]
  },
  "惧":{
    "SUBCLASS_OF":[
      "1.恐惧",
      "2.羞",
      "3.烦闷"
    ]
  },
  "恶":{
    "SUBCLASS_OF":[
      "1.憎恶",
      "2.贬责",
      "3.妒忌",
      "4.怀疑"
    ]
  },
  "惊":{
    "SUBCLASS_OF":[
      "1.惊奇"
    ]
  },
  "快乐":{
    "SUBCLASS_OF":"快乐"
  },
  "安心":{
    "SUBCLASS_OF":"安心"
  },
  "尊敬":{
    "SUBCLASS_OF":"尊敬"
  },
  "赞扬":{
    "SUBCLASS_OF":"赞扬"
  },
  "相信":{
    "SUBCLASS_OF":"相信"
  },
  "喜爱":{
    "SUBCLASS_OF":"喜爱"
  },
  "祝愿":{
    "SUBCLASS_OF":"祝愿"
  },
  "愤怒":{
    "SUBCLASS_OF":"愤怒"
  },
  "悲伤":{
    "SUBCLASS_OF":"悲伤"
  },
  "失望":{
    "SUBCLASS_OF":"失望"
  },
  "疚":{
    "SUBCLASS_OF":"疚"
  },
  "思":{
    "SUBCLASS_OF":"思"
  },
  "慌":{
    "SUBCLASS_OF":"慌"
  },
  "恐惧":{
    "SUBCLASS_OF":"恐惧"
  },
  "羞":{
    "SUBCLASS_OF":"羞"
  },
  "烦闷":{
    "SUBCLASS_OF":"烦闷"
  },
  "憎恶":{
    "SUBCLASS_OF":"憎恶"
  },
  "贬责":{
    "SUBCLASS_OF":"贬责"
  },
  "妒忌":{
    "SUBCLASS_OF":"妒忌"
  },
  "怀疑":{
    "SUBCLASS_OF":"怀疑"
  },
  "惊奇":{
    "SUBCLASS_OF":"惊奇"
  },
  "瑞雪":{
    "category":"快乐",
    "related_category":null,
    "word_class":"noun",
    "emotion_intense":5,
    "total_meanings":1,
    "word_polarity":1
  },
  "解惑":{
    "category":"赞扬",
    "related_category":"快乐",
    "word_class":"verb",
    "emotion_intense":3,
    "total_meanings":1,
    "word_polarity":1
  },
  "逞性子":{
    "category":"贬责",
    "related_category":null,
    "word_class":"verb",
    "emotion_intense":7,
    "total_meanings":1,
    "word_polarity":2
  },
  "见风转舵":{
    "category":"贬责",
    "related_category":"憎恶",
    "word_class":"idiom",
    "emotion_intense":7,
    "total_meanings":1,
    "word_polarity":2
  },
  "滑天下之大稽":{
    "category":"贬责",
    "related_category":null,
    "word_class":"idiom",
    "emotion_intense":7,
    "total_meanings":1,
    "word_polarity":2
  },
  "嫣然":{
    "category":"快乐",
    "related_category":null,
    "word_class":"adj",
    "emotion_intense":5,
    "total_meanings":1,
    "word_polarity":1
  },
  "令人鼓舞":{
    "category":"赞扬",
    "related_category":null,
    "word_class":"adj",
    "emotion_intense":5,
    "total_meanings":1,
    "word_polarity":1
  },
  "倜傥":{
    "category":"赞扬",
    "related_category":null,
    "word_class":"adj",
    "emotion_intense":5,
    "total_meanings":1,
    "word_polarity":1
  },
  "暴跳如雷":{
    "category":"愤怒",
    "related_category":null,
    "word_class":"adj",
    "emotion_intense":9,
    "total_meanings":1,
    "word_polarity":2
  },
  "视如寇仇":{
    "category":"憎恶",
    "related_category":null,
    "word_class":"idiom",
    "emotion_intense":7,
    "total_meanings":1,
    "word_polarity":2
  },
  "人浮于事":{
    "category":"贬责",
    "related_category":null,
    "word_class":"idiom",
    "emotion_intense":7,
    "total_meanings":1,
    "word_polarity":2
  },
  "珠联璧合":{
    "category":"赞扬",
    "related_category":null,
    "word_class":"idiom",
    "emotion_intense":7,
    "total_meanings":1,
    "word_polarity":1
  },
  "豺狐之心":{
    "category":"贬责",
    "related_category":"憎恶",
    "word_class":"idiom",
    "emotion_intense":7,
    "total_meanings":1,
    "word_polarity":2
  },
  "逼上梁山":{
    "category":"愤怒",
    "related_category":null,
    "word_class":"idiom",
    "emotion_intense":5,
    "total_meanings":1,
    "word_polarity":0
  },
  "袒裼裸裎":{
    "category":"贬责",
    "related_category":"赞扬",
    "word_class":"idiom",
    "emotion_intense":5,
    "total_meanings":1,
    "word_polarity":2
  },
  "得薄能鲜":{
    "category":"贬责",
    "related_category":null,
    "word_class":"idiom",
    "emotion_intense":5,
    "total_meanings":1,
    "word_polarity":2
  },
  "轻率":{
    "category":"贬责",
    "related_category":null,
    "word_class":"adj",
    "emotion_intense":5,
    "total_meanings":1,
    "word_polarity":2
  },
  "博雅":{
    "category":"赞扬",
    "related_category":null,
    "word_class":"adj",
    "emotion_intense":5,
    "total_meanings":1,
    "word_polarity":1
  },
  "大士":{
    "category":"赞扬",
    "related_category":"尊敬",
    "word_class":"noun",
    "emotion_intense":5,
    "total_meanings":1,
    "word_polarity":1
  },
  "挂记":{
    "category":"思",
    "related_category":null,
    "word_class":"verb",
    "emotion_intense":5,
    "total_meanings":1,
    "word_polarity":0
  },
  "违纪":{
    "category":"贬责",
    "related_category":null,
    "word_class":"verb",
    "emotion_intense":5,
    "total_meanings":1,
    "word_polarity":2
  },
  "心惊肉跳":{
    "category":"恐惧",
    "related_category":null,
    "word_class":"idiom",
    "emotion_intense":7,
    "total_meanings":1,
    "word_polarity":0
  },
  "徘徊":{
    "category":"烦闷",
    "related_category":null,
    "word_class":"verb",
    "emotion_intense":7,
    "total_meanings":1,
    "word_polarity":0
  },
  "清顺":{
    "category":"赞扬",
    "related_category":null,
    "word_class":"adj",
    "emotion_intense":3,
    "total_meanings":1,
    "word_polarity":0
  },
  "奖赏":{
    "category":"赞扬",
    "related_category":"快乐",
    "word_class":"noun",
    "emotion_intense":3,
    "total_meanings":1,
    "word_polarity":1
  },
  "无价值":{
    "category":"贬责",
    "related_category":null,
    "word_class":"prep",
    "emotion_intense":5,
    "total_meanings":1,
    "word_polarity":2
  },
  "气鼓鼓":{
    "category":"愤怒",
    "related_category":null,
    "word_class":"adj",
    "emotion_intense":5,
    "total_meanings":1,
    "word_polarity":0
  },
  "绵里藏针":{
    "category":"贬责",
    "related_category":"憎恶",
    "word_class":"idiom",
    "emotion_intense":7,
    "total_meanings":1,
    "word_polarity":2
  },
  "认认真真":{
    "category":"赞扬",
    "related_category":null,
    "word_class":"idiom",
    "emotion_intense":5,
    "total_meanings":1,
    "word_polarity":1
  },
  "赏心乐事":{
    "category":"快乐",
    "related_category":null,
    "word_class":"noun",
    "emotion_intense":5,
    "total_meanings":1,
    "word_polarity":1
  },
  "放松":{
    "category":"安心",
    "related_category":null,
    "word_class":"adj",
    "emotion_intense":1,
    "total_meanings":1,
    "word_polarity":0
  },
  "公正":{
    "category":"赞扬",
    "related_category":null,
    "word_class":"adj",
    "emotion_intense":5,
    "total_meanings":1,
    "word_polarity":1
  },
  "奇伟":{
    "category":"赞扬",
    "related_category":null,
    "word_class":"adj",
    "emotion_intense":7,
    "total_meanings":1,
    "word_polarity":1
  },
  "悲鸣":{
    "category":"悲伤",
    "related_category":null,
    "word_class":"adj",
    "emotion_intense":7,
    "total_meanings":1,
    "word_polarity":0
  },
  "窝心":{
    "category":"烦闷",
    "related_category":null,
    "word_class":"adj",
    "emotion_intense":5,
    "total_meanings":1,
    "word_polarity":2
  },
  "风调雨顺":{
    "category":"快乐",
    "related_category":null,
    "word_class":"idiom",
    "emotion_intense":5,
    "total_meanings":1,
    "word_polarity":1
  },
  "镂月裁云":{
    "category":"赞扬",
    "related_category":null,
    "word_class":"idiom",
    "emotion_intense":5,
    "total_meanings":1,
    "word_polarity":1
  },
  "将心比心":{
    "category":"赞扬",
    "related_category":null,
    "word_class":"idiom",
    "emotion_intense":5,
    "total_meanings":1,
    "word_polarity":1
  },
  "束手就擒":{
    "category":"贬责",
    "related_category":null,
    "word_class":"idiom",
    "emotion_intense":5,
    "total_meanings":1,
    "word_polarity":2
  },
  "十之八九":{
    "category":"相信",
    "related_category":null,
    "word_class":"idiom",
    "emotion_intense":7,
    "total_meanings":1,
    "word_polarity":1
  },
  "适得其反":{
    "category":"贬责",
    "related_category":null,
    "word_class":"idiom",
    "emotion_intense":3,
    "total_meanings":1,
    "word_polarity":2
  },
  "伐功矜能":{
    "category":"贬责",
    "related_category":null,
    "word_class":"idiom",
    "emotion_intense":5,
    "total_meanings":1,
    "word_polarity":2
  },
  "缺德":{
    "category":"贬责",
    "related_category":null,
    "word_class":"adj",
    "emotion_intense":7,
    "total_meanings":1,
    "word_polarity":2
  },
  "戴高帽子":{
    "category":"贬责",
    "related_category":null,
    "word_class":"verb",
    "emotion_intense":5,
    "total_meanings":1,
    "word_polarity":2
  },
  "出息":{
    "category":"赞扬",
    "related_category":null,
    "word_class":"noun",
    "emotion_intense":5,
    "total_meanings":1,
    "word_polarity":1
  },
  "后台":{
    "category":"贬责",
    "related_category":"憎恶",
    "word_class":"noun",
    "emotion_intense":5,
    "total_meanings":1,
    "word_polarity":2
  },
  "恭贺":{
    "category":"快乐",
    "related_category":null,
    "word_class":"verb",
    "emotion_intense":5,
    "total_meanings":1,
    "word_polarity":1
  },
  "衰亡":{
    "category":"悲伤",
    "related_category":null,
    "word_class":"verb",
    "emotion_intense":5,
    "total_meanings":1,
    "word_polarity":0
  },
  "乌七八糟":{
    "category":"贬责",
    "related_category":null,
    "word_class":"idiom",
    "emotion_intense":7,
    "total_meanings":1,
    "word_polarity":2
  },
  "气急败坏":{
    "category":"愤怒",
    "related_category":null,
    "word_class":"adj",
    "emotion_intense":9,
    "total_meanings":1,
    "word_polarity":2
  },
  "干脆":{
    "category":"赞扬",
    "related_category":null,
    "word_class":"adj",
    "emotion_intense":3,
    "total_meanings":2,
    "word_polarity":1
  },
  "志同道合":{
    "category":"喜爱",
    "related_category":null,
    "word_class":"idiom",
    "emotion_intense":3,
    "total_meanings":1,
    "word_polarity":1
  },
  "糟粕":{
    "category":"贬责",
    "related_category":null,
    "word_class":"noun",
    "emotion_intense":5,
    "total_meanings":1,
    "word_polarity":2
  },
  "严慈":{
    "category":"赞扬",
    "related_category":"尊敬",
    "word_class":"adj",
    "emotion_intense":5,
    "total_meanings":1,
    "word_polarity":1
  },
  "救荒":{
    "category":"赞扬",
    "related_category":"尊敬",
    "word_class":"verb",
    "emotion_intense":3,
    "total_meanings":1,
    "word_polarity":1
  },
  "寒伧":{
    "category":"贬责",
    "related_category":null,
    "word_class":"adj",
    "emotion_intense":7,
    "total_meanings":1,
    "word_polarity":2
  },
  "起敬":{
    "category":"尊敬",
    "related_category":null,
    "word_class":"verb",
    "emotion_intense":3,
    "total_meanings":1,
    "word_polarity":0
  },
  "气闷":{
    "category":"烦闷",
    "related_category":null,
    "word_class":"adj",
    "emotion_intense":5,
    "total_meanings":1,
    "word_polarity":0
  },
  "心黑手辣":{
    "category":"贬责",
    "related_category":"恐惧",
    "word_class":"idiom",
    "emotion_intense":9,
    "total_meanings":1,
    "word_polarity":2
  },
  "含笑":{
    "category":"快乐",
    "related_category":null,
    "word_class":"verb",
    "emotion_intense":3,
    "total_meanings":1,
    "word_polarity":0
  },
  "宽心":{
    "category":"安心",
    "related_category":null,
    "word_class":"verb",
    "emotion_intense":1,
    "total_meanings":1,
    "word_polarity":0
  },
  "仗义执言":{
    "category":"赞扬",
    "related_category":"尊敬",
    "word_class":"idiom",
    "emotion_intense":5,
    "total_meanings":1,
    "word_polarity":1
  },
  "清正":{
    "category":"赞扬",
    "related_category":"尊敬",
    "word_class":"adj",
    "emotion_intense":5,
    "total_meanings":1,
    "word_polarity":1
  },
  "生不逢辰":{
    "category":"悲伤",
    "related_category":null,
    "word_class":"idiom",
    "emotion_intense":3,
    "total_meanings":1,
    "word_polarity":0
  },
  "深仇大恨":{
    "category":"憎恶",
    "related_category":null,
    "word_class":"noun",
    "emotion_intense":9,
    "total_meanings":1,
    "word_polarity":2
  },
  "慌慌张张":{
    "category":"慌",
    "related_category":null,
    "word_class":"adj",
    "emotion_intense":3,
    "total_meanings":1,
    "word_polarity":2
  },
  "逆水行舟":{
    "category":"烦闷",
    "related_category":null,
    "word_class":"idiom",
    "emotion_intense":1,
    "total_meanings":1,
    "word_polarity":0
  },
  "蜗舍荆扉":{
    "category":"贬责",
    "related_category":null,
    "word_class":"idiom",
    "emotion_intense":3,
    "total_meanings":1,
    "word_polarity":2
  },
  "公平交易":{
    "category":"赞扬",
    "related_category":null,
    "word_class":"idiom",
    "emotion_intense":3,
    "total_meanings":1,
    "word_polarity":1
  },
  "雪虐风饕":{
    "category":"恐惧",
    "related_category":"慌",
    "word_class":"idiom",
    "emotion_intense":9,
    "total_meanings":1,
    "word_polarity":2
  },
  "知恩报恩":{
    "category":"赞扬",
    "related_category":null,
    "word_class":"idiom",
    "emotion_intense":5,
    "total_meanings":1,
    "word_polarity":1
  },
  "因小失大":{
    "category":"贬责",
    "related_category":null,
    "word_class":"idiom",
    "emotion_intense":5,
    "total_meanings":1,
    "word_polarity":2
  },
  "hiahia":{
    "category":"快乐",
    "related_category":null,
    "word_class":"nw",
    "emotion_intense":3,
    "total_meanings":1,
    "word_polarity":0
  },
  "佻巧":{
    "category":"贬责",
    "related_category":"憎恶",
    "word_class":"adj",
    "emotion_intense":3,
    "total_meanings":1,
    "word_polarity":2
  },
  "白字":{
    "category":"贬责",
    "related_category":null,
    "word_class":"noun",
    "emotion_intense":1,
    "total_meanings":1,
    "word_polarity":2
  },
  "倒灶":{
    "category":"烦闷",
    "related_category":null,
    "word_class":"verb",
    "emotion_intense":5,
    "total_meanings":1,
    "word_polarity":2
  },
  "僵化":{
    "category":"贬责",
    "related_category":null,
    "word_class":"adj",
    "emotion_intense":3,
    "total_meanings":1,
    "word_polarity":2
  },
  "光华":{
    "category":"赞扬",
    "related_category":"喜爱",
    "word_class":"noun",
    "emotion_intense":7,
    "total_meanings":1,
    "word_polarity":1
  },
  "嗒丧":{
    "category":"贬责",
    "related_category":"失望",
    "word_class":"verb",
    "emotion_intense":5,
    "total_meanings":1,
    "word_polarity":2
  },
  "名不虚传":{
    "category":"赞扬",
    "related_category":null,
    "word_class":"idiom",
    "emotion_intense":5,
    "total_meanings":1,
    "word_polarity":1
  },
  "缓解":{
    "category":"安心",
    "related_category":null,
    "word_class":"verb",
    "emotion_intense":3,
    "total_meanings":1,
    "word_polarity":0
  },
  "奸邪":{
    "category":"贬责",
    "related_category":"憎恶",
    "word_class":"adj",
    "emotion_intense":9,
    "total_meanings":1,
    "word_polarity":2
  },
  "请教":{
    "category":"尊敬",
    "related_category":null,
    "word_class":"adj",
    "emotion_intense":3,
    "total_meanings":1,
    "word_polarity":1
  },
  "哀婉":{
    "category":"悲伤",
    "related_category":"失望",
    "word_class":"adj",
    "emotion_intense":1,
    "total_meanings":1,
    "word_polarity":2
  },
  "不成器":{
    "category":"贬责",
    "related_category":null,
    "word_class":"adj",
    "emotion_intense":5,
    "total_meanings":1,
    "word_polarity":2
  },
  "瑕不掩瑜":{
    "category":"赞扬",
    "related_category":null,
    "word_class":"idiom",
    "emotion_intense":5,
    "total_meanings":1,
    "word_polarity":1
  },
  "拘礼":{
    "category":"贬责",
    "related_category":null,
    "word_class":"verb",
    "emotion_intense":3,
    "total_meanings":1,
    "word_polarity":2
  },
  "荷花":{
    "category":"赞扬",
    "related_category":"喜爱",
    "word_class":"noun",
    "emotion_intense":1,
    "total_meanings":1,
    "word_polarity":0
  },
  "稳扎稳打":{
    "category":"赞扬",
    "related_category":null,
    "word_class":"idiom",
    "emotion_intense":9,
    "total_meanings":1,
    "word_polarity":1
  },
  "宠幸":{
    "category":"喜爱",
    "related_category":null,
    "word_class":"verb",
    "emotion_intense":5,
    "total_meanings":1,
    "word_polarity":0
  },
  "傲然":{
    "category":"赞扬",
    "related_category":"贬责",
    "word_class":"adj",
    "emotion_intense":1,
    "total_meanings":1,
    "word_polarity":1
  },
  "刚烈":{
    "category":"赞扬",
    "related_category":null,
    "word_class":"adj",
    "emotion_intense":5,
    "total_meanings":1,
    "word_polarity":1
  },
  "首屈一指":{
    "category":"赞扬",
    "related_category":null,
    "word_class":"adj",
    "emotion_intense":9,
    "total_meanings":1,
    "word_polarity":1
  },
  "盘踞":{
    "category":"憎恶",
    "related_category":"贬责",
    "word_class":"verb",
    "emotion_intense":5,
    "total_meanings":1,
    "word_polarity":2
  },
  "惨怛":{
    "category":"恐惧",
    "related_category":"悲伤",
    "word_class":"adj",
    "emotion_intense":3,
    "total_meanings":1,
    "word_polarity":0
  },
  "结驷联骑":{
    "category":"贬责",
    "related_category":"憎恶",
    "word_class":"idiom",
    "emotion_intense":9,
    "total_meanings":1,
    "word_polarity":2
  },
  "亘古未有":{
    "category":"惊奇",
    "related_category":"赞扬",
    "word_class":"idiom",
    "emotion_intense":9,
    "total_meanings":1,
    "word_polarity":1
  },
  "依违两可":{
    "category":"贬责",
    "related_category":"怀疑",
    "word_class":"idiom",
    "emotion_intense":3,
    "total_meanings":1,
    "word_polarity":2
  },
  "大含细入":{
    "category":"赞扬",
    "related_category":null,
    "word_class":"idiom",
    "emotion_intense":7,
    "total_meanings":1,
    "word_polarity":1
  },
  "孟母三迁":{
    "category":"赞扬",
    "related_category":null,
    "word_class":"idiom",
    "emotion_intense":3,
    "total_meanings":1,
    "word_polarity":1
  },
  "有进无退":{
    "category":"赞扬",
    "related_category":null,
    "word_class":"idiom",
    "emotion_intense":7,
    "total_meanings":1,
    "word_polarity":1
  },
  "漠视":{
    "category":"贬责",
    "related_category":null,
    "word_class":"verb",
    "emotion_intense":3,
    "total_meanings":1,
    "word_polarity":2
  },
  "负心":{
    "category":"贬责",
    "related_category":null,
    "word_class":"verb",
    "emotion_intense":5,
    "total_meanings":1,
    "word_polarity":2
  },
  "冲霄":{
    "category":"赞扬",
    "related_category":null,
    "word_class":"verb",
    "emotion_intense":3,
    "total_meanings":1,
    "word_polarity":1
  },
  "坏水":{
    "category":"憎恶",
    "related_category":"贬责",
    "word_class":"noun",
    "emotion_intense":3,
    "total_meanings":1,
    "word_polarity":2
  },
  "逆产":{
    "category":"贬责",
    "related_category":"憎恶",
    "word_class":"noun",
    "emotion_intense":3,
    "total_meanings":1,
    "word_polarity":2
  },
  "违规":{
    "category":"贬责",
    "related_category":null,
    "word_class":"verb",
    "emotion_intense":5,
    "total_meanings":1,
    "word_polarity":2
  },
  "难看":{
    "category":"贬责",
    "related_category":null,
    "word_class":"adj",
    "emotion_intense":5,
    "total_meanings":1,
    "word_polarity":2
  },
  "治世":{
    "category":"赞扬",
    "related_category":null,
    "word_class":"noun",
    "emotion_intense":7,
    "total_meanings":1,
    "word_polarity":1
  },
  "重任":{
    "category":"相信",
    "related_category":"尊敬",
    "word_class":"noun",
    "emotion_intense":5,
    "total_meanings":1,
    "word_polarity":0
  },
  "指斥":{
    "category":"贬责",
    "related_category":null,
    "word_class":"verb",
    "emotion_intense":5,
    "total_meanings":1,
    "word_polarity":2
  },
  "家珍":{
    "category":"赞扬",
    "related_category":null,
    "word_class":"noun",
    "emotion_intense":5,
    "total_meanings":1,
    "word_polarity":1
  },
  "谐趣横生":{
    "category":"赞扬",
    "related_category":"快乐",
    "word_class":"idiom",
    "emotion_intense":9,
    "total_meanings":1,
    "word_polarity":1
  },
  "惊奇不已":{
    "category":"惊奇",
    "related_category":null,
    "word_class":"adj",
    "emotion_intense":5,
    "total_meanings":1,
    "word_polarity":0
  },
  "没头脑":{
    "category":"贬责",
    "related_category":null,
    "word_class":"prep",
    "emotion_intense":5,
    "total_meanings":1,
    "word_polarity":2
  },
  "天字第一号":{
    "category":"赞扬",
    "related_category":null,
    "word_class":"adj",
    "emotion_intense":9,
    "total_meanings":1,
    "word_polarity":0
  },
  "内敛":{
    "category":"赞扬",
    "related_category":null,
    "word_class":"adj",
    "emotion_intense":1,
    "total_meanings":1,
    "word_polarity":1
  },
  "青睐":{
    "category":"喜爱",
    "related_category":null,
    "word_class":"verb",
    "emotion_intense":3,
    "total_meanings":1,
    "word_polarity":1
  },
  "典范":{
    "category":"赞扬",
    "related_category":null,
    "word_class":"noun",
    "emotion_intense":7,
    "total_meanings":1,
    "word_polarity":1
  },
  "情坚金石":{
    "category":"赞扬",
    "related_category":null,
    "word_class":"idiom",
    "emotion_intense":5,
    "total_meanings":1,
    "word_polarity":1
  },
  "易怒":{
    "category":"愤怒",
    "related_category":null,
    "word_class":"adj",
    "emotion_intense":1,
    "total_meanings":1,
    "word_polarity":0
  },
  "狼心狗肺":{
    "category":"憎恶",
    "related_category":null,
    "word_class":"adj",
    "emotion_intense":7,
    "total_meanings":1,
    "word_polarity":2
  },
  "自贻伊戚":{
    "category":"烦闷",
    "related_category":null,
    "word_class":"idiom",
    "emotion_intense":1,
    "total_meanings":1,
    "word_polarity":2
  },
  "经纶济世":{
    "category":"赞扬",
    "related_category":null,
    "word_class":"idiom",
    "emotion_intense":7,
    "total_meanings":1,
    "word_polarity":1
  },
  "宾至如归":{
    "category":"赞扬",
    "related_category":null,
    "word_class":"idiom",
    "emotion_intense":1,
    "total_meanings":1,
    "word_polarity":1
  },
  "退思补过":{
    "category":"疚",
    "related_category":null,
    "word_class":"idiom",
    "emotion_intense":3,
    "total_meanings":1,
    "word_polarity":0
  },
  "人命危浅":{
    "category":"悲伤",
    "related_category":null,
    "word_class":"idiom",
    "emotion_intense":5,
    "total_meanings":1,
    "word_polarity":2
  },
  "不败之地":{
    "category":"相信",
    "related_category":null,
    "word_class":"idiom",
    "emotion_intense":9,
    "total_meanings":1,
    "word_polarity":1
  },
  "梁上君子":{
    "category":"贬责",
    "related_category":null,
    "word_class":"idiom",
    "emotion_intense":5,
    "total_meanings":1,
    "word_polarity":2
  },
  "有则改之，无则加勉":{
    "category":"尊敬",
    "related_category":null,
    "word_class":"idiom",
    "emotion_intense":3,
    "total_meanings":1,
    "word_polarity":1
  },
  "恶狠狠":{
    "category":"憎恶",
    "related_category":"贬责",
    "word_class":"idiom",
    "emotion_intense":7,
    "total_meanings":1,
    "word_polarity":2
  },
  "淫荡":{
    "category":"贬责",
    "related_category":"憎恶",
    "word_class":"adj",
    "emotion_intense":7,
    "total_meanings":1,
    "word_polarity":2
  },
  "魑魅":{
    "category":"贬责",
    "related_category":"憎恶",
    "word_class":"noun",
    "emotion_intense":7,
    "total_meanings":1,
    "word_polarity":2
  },
  "鬼混":{
    "category":"贬责",
    "related_category":"憎恶",
    "word_class":"verb",
    "emotion_intense":5,
    "total_meanings":1,
    "word_polarity":2
  },
  "落马":{
    "category":"贬责",
    "related_category":null,
    "word_class":"verb",
    "emotion_intense":3,
    "total_meanings":1,
    "word_polarity":2
  },
  "啬刻":{
    "category":"贬责",
    "related_category":null,
    "word_class":"adj",
    "emotion_intense":3,
    "total_meanings":1,
    "word_polarity":2
  },
  "大师":{
    "category":"尊敬",
    "related_category":"赞扬",
    "word_class":"noun",
    "emotion_intense":7,
    "total_meanings":1,
    "word_polarity":1
  },
  "旷达":{
    "category":"赞扬",
    "related_category":null,
    "word_class":"adj",
    "emotion_intense":5,
    "total_meanings":1,
    "word_polarity":1
  },
  "纸上谈兵":{
    "category":"贬责",
    "related_category":null,
    "word_class":"verb",
    "emotion_intense":5,
    "total_meanings":1,
    "word_polarity":2
  },
  "沾沾自喜":{
    "category":"贬责",
    "related_category":"憎恶",
    "word_class":"idiom",
    "emotion_intense":1,
    "total_meanings":1,
    "word_polarity":2
  },
  "道贺":{
    "category":"快乐",
    "related_category":null,
    "word_class":"verb",
    "emotion_intense":1,
    "total_meanings":1,
    "word_polarity":0
  },
  "封建":{
    "category":"贬责",
    "related_category":null,
    "word_class":"adj",
    "emotion_intense":3,
    "total_meanings":1,
    "word_polarity":2
  },
  "清闲":{
    "category":"快乐",
    "related_category":null,
    "word_class":"adj",
    "emotion_intense":3,
    "total_meanings":1,
    "word_polarity":0
  },
  "反其道而行之":{
    "category":"贬责",
    "related_category":"赞扬",
    "word_class":"idiom",
    "emotion_intense":3,
    "total_meanings":1,
    "word_polarity":0
  },
  "慷慨陈词":{
    "category":"赞扬",
    "related_category":null,
    "word_class":"idiom",
    "emotion_intense":3,
    "total_meanings":1,
    "word_polarity":1
  },
  "用尽心机":{
    "category":"贬责",
    "related_category":null,
    "word_class":"idiom",
    "emotion_intense":3,
    "total_meanings":1,
    "word_polarity":2
  },
  "告非":{
    "category":"愤怒",
    "related_category":null,
    "word_class":"nw",
    "emotion_intense":3,
    "total_meanings":1,
    "word_polarity":1
  },
  "祈盼":{
    "category":"思",
    "related_category":null,
    "word_class":"verb",
    "emotion_intense":3,
    "total_meanings":1,
    "word_polarity":0
  },
  "纯情":{
    "category":"赞扬",
    "related_category":null,
    "word_class":"adj",
    "emotion_intense":5,
    "total_meanings":1,
    "word_polarity":1
  },
  "率直":{
    "category":"赞扬",
    "related_category":null,
    "word_class":"adj",
    "emotion_intense":5,
    "total_meanings":1,
    "word_polarity":1
  },
  "要好":{
    "category":"喜爱",
    "related_category":null,
    "word_class":"adj",
    "emotion_intense":5,
    "total_meanings":1,
    "word_polarity":1
  },
  "暮气沉沉":{
    "category":"烦闷",
    "related_category":"贬责",
    "word_class":"idiom",
    "emotion_intense":5,
    "total_meanings":1,
    "word_polarity":2
  },
  "夫子自道":{
    "category":"贬责",
    "related_category":null,
    "word_class":"idiom",
    "emotion_intense":5,
    "total_meanings":1,
    "word_polarity":2
  },
  "能工巧匠":{
    "category":"赞扬",
    "related_category":null,
    "word_class":"idiom",
    "emotion_intense":5,
    "total_meanings":1,
    "word_polarity":1
  },
  "勇往直前":{
    "category":"赞扬",
    "related_category":null,
    "word_class":"idiom",
    "emotion_intense":5,
    "total_meanings":1,
    "word_polarity":1
  },
  "软骨头":{
    "category":"贬责",
    "related_category":null,
    "word_class":"noun",
    "emotion_intense":5,
    "total_meanings":1,
    "word_polarity":2
  },
  "大骂":{
    "category":"贬责",
    "related_category":null,
    "word_class":"verb",
    "emotion_intense":5,
    "total_meanings":1,
    "word_polarity":2
  },
  "责难":{
    "category":"贬责",
    "related_category":null,
    "word_class":"verb",
    "emotion_intense":5,
    "total_meanings":1,
    "word_polarity":2
  },
  "千真万确":{
    "category":"相信",
    "related_category":null,
    "word_class":"adj",
    "emotion_intense":7,
    "total_meanings":1,
    "word_polarity":0
  },
  "只许州官放火，不许百姓点灯":{
    "category":"贬责",
    "related_category":"憎恶",
    "word_class":"idiom",
    "emotion_intense":7,
    "total_meanings":1,
    "word_polarity":2
  },
  "以血洗血":{
    "category":"憎恶",
    "related_category":null,
    "word_class":"idiom",
    "emotion_intense":7,
    "total_meanings":1,
    "word_polarity":2
  },
  "憧憬":{
    "category":"祝愿",
    "related_category":null,
    "word_class":"verb",
    "emotion_intense":7,
    "total_meanings":1,
    "word_polarity":0
  },
  "五星级":{
    "category":"赞扬",
    "related_category":null,
    "word_class":"adj",
    "emotion_intense":9,
    "total_meanings":1,
    "word_polarity":1
  },
  "里通外国":{
    "category":"贬责",
    "related_category":null,
    "word_class":"idiom",
    "emotion_intense":9,
    "total_meanings":1,
    "word_polarity":2
  },
  "嘉奖":{
    "category":"赞扬",
    "related_category":"尊敬",
    "word_class":"verb",
    "emotion_intense":9,
    "total_meanings":1,
    "word_polarity":1
  },
  "阴错阳差":{
    "category":"惊奇",
    "related_category":null,
    "word_class":"idiom",
    "emotion_intense":3,
    "total_meanings":1,
    "word_polarity":0
  },
  "足色":{
    "category":"赞扬",
    "related_category":null,
    "word_class":"adj",
    "emotion_intense":5,
    "total_meanings":1,
    "word_polarity":1
  },
  "叫苦":{
    "category":"烦闷",
    "related_category":null,
    "word_class":"verb",
    "emotion_intense":5,
    "total_meanings":1,
    "word_polarity":0
  },
  "囊中羞涩":{
    "category":"烦闷",
    "related_category":null,
    "word_class":"idiom",
    "emotion_intense":7,
    "total_meanings":1,
    "word_polarity":2
  },
  "一统天下":{
    "category":"赞扬",
    "related_category":null,
    "word_class":"idiom",
    "emotion_intense":9,
    "total_meanings":1,
    "word_polarity":1
  },
  "含在嘴里怕化了，捏在手里怕碎了":{
    "category":"喜爱",
    "related_category":null,
    "word_class":"idiom",
    "emotion_intense":9,
    "total_meanings":1,
    "word_polarity":0
  },
  "好学":{
    "category":"赞扬",
    "related_category":null,
    "word_class":"adj",
    "emotion_intense":5,
    "total_meanings":1,
    "word_polarity":1
  },
  "水灵灵":{
    "category":"赞扬",
    "related_category":null,
    "word_class":"adj",
    "emotion_intense":5,
    "total_meanings":1,
    "word_polarity":1
  },
  "六月飞霜":{
    "category":"悲伤",
    "related_category":null,
    "word_class":"idiom",
    "emotion_intense":9,
    "total_meanings":1,
    "word_polarity":0
  },
  "腻味":{
    "category":"烦闷",
    "related_category":null,
    "word_class":"adj",
    "emotion_intense":1,
    "total_meanings":1,
    "word_polarity":2
  },
  "趁人之危":{
    "category":"贬责",
    "related_category":null,
    "word_class":"idiom",
    "emotion_intense":9,
    "total_meanings":1,
    "word_polarity":2
  },
  "嚎啕大哭":{
    "category":"悲伤",
    "related_category":null,
    "word_class":"idiom",
    "emotion_intense":9,
    "total_meanings":1,
    "word_polarity":0
  },
  "殚财竭力":{
    "category":"赞扬",
    "related_category":null,
    "word_class":"idiom",
    "emotion_intense":5,
    "total_meanings":1,
    "word_polarity":1
  },
  "官样文章":{
    "category":"憎恶",
    "related_category":null,
    "word_class":"idiom",
    "emotion_intense":5,
    "total_meanings":1,
    "word_polarity":2
  },
  "宽人大度":{
    "category":"赞扬",
    "related_category":null,
    "word_class":"idiom",
    "emotion_intense":5,
    "total_meanings":1,
    "word_polarity":1
  },
  "单复之术":{
    "category":"惊奇",
    "related_category":null,
    "word_class":"idiom",
    "emotion_intense":1,
    "total_meanings":1,
    "word_polarity":0
  },
  "庞杂":{
    "category":"贬责",
    "related_category":"憎恶",
    "word_class":"adj",
    "emotion_intense":1,
    "total_meanings":1,
    "word_polarity":2
  },
  "见死不救":{
    "category":"贬责",
    "related_category":"快乐",
    "word_class":"idiom",
    "emotion_intense":7,
    "total_meanings":1,
    "word_polarity":2
  },
  "逞性":{
    "category":"贬责",
    "related_category":null,
    "word_class":"verb",
    "emotion_intense":7,
    "total_meanings":1,
    "word_polarity":2
  },
  "得时":{
    "category":"快乐",
    "related_category":null,
    "word_class":"verb",
    "emotion_intense":3,
    "total_meanings":1,
    "word_polarity":1
  },
  "恭正":{
    "category":"尊敬",
    "related_category":null,
    "word_class":"adj",
    "emotion_intense":3,
    "total_meanings":1,
    "word_polarity":1
  },
  "妄动":{
    "category":"贬责",
    "related_category":null,
    "word_class":"verb",
    "emotion_intense":5,
    "total_meanings":1,
    "word_polarity":2
  },
  "远大":{
    "category":"赞扬",
    "related_category":"憎恶",
    "word_class":"adj",
    "emotion_intense":5,
    "total_meanings":1,
    "word_polarity":1
  },
  "一往无前":{
    "category":"赞扬",
    "related_category":"憎恶",
    "word_class":"adj",
    "emotion_intense":5,
    "total_meanings":1,
    "word_polarity":1
  },
  "宗派":{
    "category":"贬责",
    "related_category":null,
    "word_class":"noun",
    "emotion_intense":5,
    "total_meanings":1,
    "word_polarity":2
  },
  "gx":{
    "category":"赞扬",
    "related_category":null,
    "word_class":"nw",
    "emotion_intense":7,
    "total_meanings":1,
    "word_polarity":1
  },
  "匀调":{
    "category":"赞扬",
    "related_category":null,
    "word_class":"adj",
    "emotion_intense":3,
    "total_meanings":1,
    "word_polarity":1
  },
  "百读不厌":{
    "category":"喜爱",
    "related_category":null,
    "word_class":"idiom",
    "emotion_intense":7,
    "total_meanings":1,
    "word_polarity":1
  },
  "叫化子拾黄金－乐不可支":{
    "category":"快乐",
    "related_category":null,
    "word_class":"idiom",
    "emotion_intense":7,
    "total_meanings":1,
    "word_polarity":0
  },
  "救困扶危":{
    "category":"赞扬",
    "related_category":null,
    "word_class":"idiom",
    "emotion_intense":7,
    "total_meanings":1,
    "word_polarity":1
  },
  "得逞":{
    "category":"憎恶",
    "related_category":null,
    "word_class":"adj",
    "emotion_intense":5,
    "total_meanings":1,
    "word_polarity":2
  },
  "铁证如山":{
    "category":"相信",
    "related_category":null,
    "word_class":"idiom",
    "emotion_intense":3,
    "total_meanings":1,
    "word_polarity":0
  },
  "汗流满面":{
    "category":"慌",
    "related_category":null,
    "word_class":"idiom",
    "emotion_intense":1,
    "total_meanings":1,
    "word_polarity":0
  },
  "轻裘缓带":{
    "category":"赞扬",
    "related_category":null,
    "word_class":"idiom",
    "emotion_intense":5,
    "total_meanings":1,
    "word_polarity":1
  },
  "庇护":{
    "category":"贬责",
    "related_category":null,
    "word_class":"verb",
    "emotion_intense":3,
    "total_meanings":1,
    "word_polarity":2
  },
  "耽误":{
    "category":"贬责",
    "related_category":null,
    "word_class":"verb",
    "emotion_intense":3,
    "total_meanings":1,
    "word_polarity":2
  },
  "为害":{
    "category":"贬责",
    "related_category":null,
    "word_class":"verb",
    "emotion_intense":7,
    "total_meanings":1,
    "word_polarity":2
  },
  "风骨":{
    "category":"赞扬",
    "related_category":null,
    "word_class":"noun",
    "emotion_intense":7,
    "total_meanings":1,
    "word_polarity":1
  },
  "欢跃":{
    "category":"快乐",
    "related_category":null,
    "word_class":"verb",
    "emotion_intense":5,
    "total_meanings":1,
    "word_polarity":0
  },
  "魁梧奇伟":{
    "category":"赞扬",
    "related_category":null,
    "word_class":"idiom",
    "emotion_intense":7,
    "total_meanings":1,
    "word_polarity":1
  },
  "千锤百炼":{
    "category":"赞扬",
    "related_category":null,
    "word_class":"adj",
    "emotion_intense":7,
    "total_meanings":1,
    "word_polarity":1
  },
  "治罪":{
    "category":"贬责",
    "related_category":null,
    "word_class":"verb",
    "emotion_intense":5,
    "total_meanings":1,
    "word_polarity":0
  },
  "螳螂捕蝉，黄雀在后":{
    "category":"贬责",
    "related_category":null,
    "word_class":"idiom",
    "emotion_intense":3,
    "total_meanings":1,
    "word_polarity":0
  },
  "两姓之好":{
    "category":"快乐",
    "related_category":null,
    "word_class":"idiom",
    "emotion_intense":5,
    "total_meanings":1,
    "word_polarity":0
  },
  "贪生怕死":{
    "category":"贬责",
    "related_category":"憎恶",
    "word_class":"idiom",
    "emotion_intense":7,
    "total_meanings":1,
    "word_polarity":2
  },
  "官气":{
    "category":"贬责",
    "related_category":"憎恶",
    "word_class":"noun",
    "emotion_intense":5,
    "total_meanings":1,
    "word_polarity":2
  },
  "前程似锦":{
    "category":"赞扬",
    "related_category":"贬责",
    "word_class":"idiom",
    "emotion_intense":9,
    "total_meanings":1,
    "word_polarity":0
  },
  "姣翠":{
    "category":"赞扬",
    "related_category":"快乐",
    "word_class":"adj",
    "emotion_intense":5,
    "total_meanings":1,
    "word_polarity":1
  },
  "都丽":{
    "category":"赞扬",
    "related_category":"喜爱",
    "word_class":"adj",
    "emotion_intense":5,
    "total_meanings":1,
    "word_polarity":1
  },
  "忠信":{
    "category":"赞扬",
    "related_category":"相信",
    "word_class":"adj",
    "emotion_intense":5,
    "total_meanings":1,
    "word_polarity":1
  },
  "心软":{
    "category":"相信",
    "related_category":null,
    "word_class":"noun",
    "emotion_intense":5,
    "total_meanings":1,
    "word_polarity":0
  },
  "面墙而立":{
    "category":"贬责",
    "related_category":null,
    "word_class":"idiom",
    "emotion_intense":5,
    "total_meanings":1,
    "word_polarity":2
  },
  "天与人归":{
    "category":"赞扬",
    "related_category":null,
    "word_class":"idiom",
    "emotion_intense":9,
    "total_meanings":1,
    "word_polarity":1
  },
  "彫虫篆刻":{
    "category":"贬责",
    "related_category":null,
    "word_class":"idiom",
    "emotion_intense":5,
    "total_meanings":1,
    "word_polarity":2
  },
  "赏贤使能":{
    "category":"赞扬",
    "related_category":null,
    "word_class":"idiom",
    "emotion_intense":5,
    "total_meanings":1,
    "word_polarity":1
  },
  "暴风雨":{
    "category":"恐惧",
    "related_category":null,
    "word_class":"noun",
    "emotion_intense":5,
    "total_meanings":1,
    "word_polarity":2
  },
  "洽博多闻":{
    "category":"赞扬",
    "related_category":null,
    "word_class":"idiom",
    "emotion_intense":7,
    "total_meanings":1,
    "word_polarity":1
  },
  "草长莺飞":{
    "category":"赞扬",
    "related_category":null,
    "word_class":"idiom",
    "emotion_intense":7,
    "total_meanings":1,
    "word_polarity":1
  },
  "健步如飞":{
    "category":"赞扬",
    "related_category":null,
    "word_class":"idiom",
    "emotion_intense":7,
    "total_meanings":1,
    "word_polarity":1
  },
  "马去马归":{
    "category":"慌",
    "related_category":null,
    "word_class":"idiom",
    "emotion_intense":3,
    "total_meanings":1,
    "word_polarity":2
  },
  "古董":{
    "category":"贬责",
    "related_category":null,
    "word_class":"noun",
    "emotion_intense":5,
    "total_meanings":2,
    "word_polarity":2
  },
  "守口如瓶":{
    "category":"赞扬",
    "related_category":null,
    "word_class":"idiom",
    "emotion_intense":7,
    "total_meanings":1,
    "word_polarity":1
  },
  "进退失措":{
    "category":"慌",
    "related_category":null,
    "word_class":"idiom",
    "emotion_intense":5,
    "total_meanings":1,
    "word_polarity":2
  },
  "邹衍谈天":{
    "category":"赞扬",
    "related_category":null,
    "word_class":"idiom",
    "emotion_intense":7,
    "total_meanings":1,
    "word_polarity":1
  },
  "贪生畏死":{
    "category":"贬责",
    "related_category":null,
    "word_class":"idiom",
    "emotion_intense":9,
    "total_meanings":1,
    "word_polarity":2
  },
  "飞灾横祸":{
    "category":"恐惧",
    "related_category":null,
    "word_class":"idiom",
    "emotion_intense":5,
    "total_meanings":1,
    "word_polarity":2
  },
  "助兴":{
    "category":"喜爱",
    "related_category":null,
    "word_class":"verb",
    "emotion_intense":7,
    "total_meanings":1,
    "word_polarity":1
  },
  "闲神野鬼":{
    "category":"贬责",
    "related_category":null,
    "word_class":"idiom",
    "emotion_intense":3,
    "total_meanings":1,
    "word_polarity":2
  },
  "东家效颦":{
    "category":"贬责",
    "related_category":null,
    "word_class":"idiom",
    "emotion_intense":5,
    "total_meanings":1,
    "word_polarity":2
  },
  "临深履薄":{
    "category":"恐惧",
    "related_category":null,
    "word_class":"idiom",
    "emotion_intense":5,
    "total_meanings":1,
    "word_polarity":2
  },
  "闲愁万种":{
    "category":"烦闷",
    "related_category":null,
    "word_class":"idiom",
    "emotion_intense":5,
    "total_meanings":1,
    "word_polarity":0
  },
  "渊海":{
    "category":"赞扬",
    "related_category":null,
    "word_class":"noun",
    "emotion_intense":7,
    "total_meanings":1,
    "word_polarity":1
  },
  "著作":{
    "category":"尊敬",
    "related_category":null,
    "word_class":"noun",
    "emotion_intense":7,
    "total_meanings":1,
    "word_polarity":1
  },
  "诛尽杀绝":{
    "category":"憎恶",
    "related_category":null,
    "word_class":"idiom",
    "emotion_intense":7,
    "total_meanings":1,
    "word_polarity":2
  },
  "不稼不穑":{
    "category":"贬责",
    "related_category":null,
    "word_class":"adj",
    "emotion_intense":5,
    "total_meanings":1,
    "word_polarity":2
  },
  "雍容雅步":{
    "category":"赞扬",
    "related_category":null,
    "word_class":"idiom",
    "emotion_intense":9,
    "total_meanings":1,
    "word_polarity":1
  },
  "飞檐走壁":{
    "category":"赞扬",
    "related_category":null,
    "word_class":"idiom",
    "emotion_intense":5,
    "total_meanings":1,
    "word_polarity":1
  },
  "劈里啪啦":{
    "category":"祝愿",
    "related_category":null,
    "word_class":"adj",
    "emotion_intense":5,
    "total_meanings":1,
    "word_polarity":0
  },
  "慢藏诲盗":{
    "category":"贬责",
    "related_category":null,
    "word_class":"idiom",
    "emotion_intense":5,
    "total_meanings":1,
    "word_polarity":2
  },
  "教唆犯":{
    "category":"贬责",
    "related_category":null,
    "word_class":"noun",
    "emotion_intense":7,
    "total_meanings":1,
    "word_polarity":2
  },
  "枉费工夫":{
    "category":"悲伤",
    "related_category":null,
    "word_class":"idiom",
    "emotion_intense":7,
    "total_meanings":1,
    "word_polarity":2
  },
  "面面相睹":{
    "category":"恐惧",
    "related_category":null,
    "word_class":"idiom",
    "emotion_intense":4,
    "total_meanings":1,
    "word_polarity":2
  },
  "便当":{
    "category":"快乐",
    "related_category":null,
    "word_class":"adj",
    "emotion_intense":5,
    "total_meanings":1,
    "word_polarity":1
  },
  "能事":{
    "category":"赞扬",
    "related_category":null,
    "word_class":"noun",
    "emotion_intense":5,
    "total_meanings":1,
    "word_polarity":1
  },
  "脂膏莫润":{
    "category":"赞扬",
    "related_category":null,
    "word_class":"idiom",
    "emotion_intense":5,
    "total_meanings":1,
    "word_polarity":1
  },
  "死乞百赖":{
    "category":"贬责",
    "related_category":null,
    "word_class":"idiom",
    "emotion_intense":5,
    "total_meanings":1,
    "word_polarity":2
  },
  "上无片瓦,下无插针之地":{
    "category":"烦闷",
    "related_category":null,
    "word_class":"idiom",
    "emotion_intense":5,
    "total_meanings":1,
    "word_polarity":2
  },
  "问一答十":{
    "category":"赞扬",
    "related_category":null,
    "word_class":"idiom",
    "emotion_intense":9,
    "total_meanings":1,
    "word_polarity":1
  },
  "扣人心弦":{
    "category":"尊敬",
    "related_category":null,
    "word_class":"idiom",
    "emotion_intense":7,
    "total_meanings":1,
    "word_polarity":1
  },
  "肉刑":{
    "category":"恐惧",
    "related_category":null,
    "word_class":"noun",
    "emotion_intense":7,
    "total_meanings":1,
    "word_polarity":0
  },
  "狗心狗行":{
    "category":"憎恶",
    "related_category":null,
    "word_class":"idiom",
    "emotion_intense":9,
    "total_meanings":1,
    "word_polarity":2
  },
  "闹意见":{
    "category":"贬责",
    "related_category":null,
    "word_class":"verb",
    "emotion_intense":5,
    "total_meanings":1,
    "word_polarity":2
  },
  "巴儿狗":{
    "category":"贬责",
    "related_category":null,
    "word_class":"noun",
    "emotion_intense":3,
    "total_meanings":2,
    "word_polarity":2
  },
  "负屈衔冤":{
    "category":"愤怒",
    "related_category":null,
    "word_class":"idiom",
    "emotion_intense":7,
    "total_meanings":1,
    "word_polarity":0
  },
  "奇勋":{
    "category":"赞扬",
    "related_category":null,
    "word_class":"noun",
    "emotion_intense":9,
    "total_meanings":1,
    "word_polarity":1
  },
  "亲痛仇快":{
    "category":"悲伤",
    "related_category":null,
    "word_class":"idiom",
    "emotion_intense":7,
    "total_meanings":1,
    "word_polarity":2
  },
  "道头知尾":{
    "category":"赞扬",
    "related_category":null,
    "word_class":"idiom",
    "emotion_intense":5,
    "total_meanings":1,
    "word_polarity":1
  },
  "匕首":{
    "category":"恐惧",
    "related_category":null,
    "word_class":"noun",
    "emotion_intense":5,
    "total_meanings":1,
    "word_polarity":2
  },
  "千载一弹":{
    "category":"安心",
    "related_category":null,
    "word_class":"idiom",
    "emotion_intense":9,
    "total_meanings":1,
    "word_polarity":1
  },
  "引绳切墨":{
    "category":"赞扬",
    "related_category":null,
    "word_class":"idiom",
    "emotion_intense":5,
    "total_meanings":1,
    "word_polarity":1
  },
  "邻女詈人":{
    "category":"贬责",
    "related_category":null,
    "word_class":"idiom",
    "emotion_intense":1,
    "total_meanings":1,
    "word_polarity":0
  },
  "如汤泼雪":{
    "category":"相信",
    "related_category":null,
    "word_class":"idiom",
    "emotion_intense":5,
    "total_meanings":1,
    "word_polarity":1
  },
  "口服心服":{
    "category":"相信",
    "related_category":null,
    "word_class":"idiom",
    "emotion_intense":7,
    "total_meanings":1,
    "word_polarity":1
  },
  "狗嘴里吐不出象牙":{
    "category":"愤怒",
    "related_category":null,
    "word_class":"idiom",
    "emotion_intense":3,
    "total_meanings":1,
    "word_polarity":2
  },
  "众口一词":{
    "category":"相信",
    "related_category":null,
    "word_class":"idiom",
    "emotion_intense":5,
    "total_meanings":1,
    "word_polarity":0
  },
  "威迫利诱":{
    "category":"贬责",
    "related_category":null,
    "word_class":"idiom",
    "emotion_intense":9,
    "total_meanings":1,
    "word_polarity":2
  },
  "头上著头":{
    "category":"贬责",
    "related_category":null,
    "word_class":"idiom",
    "emotion_intense":7,
    "total_meanings":1,
    "word_polarity":2
  },
  "赔笑":{
    "category":"恐惧",
    "related_category":null,
    "word_class":"adj",
    "emotion_intense":6,
    "total_meanings":1,
    "word_polarity":0
  },
  "钦定":{
    "category":"相信",
    "related_category":null,
    "word_class":"noun",
    "emotion_intense":5,
    "total_meanings":1,
    "word_polarity":1
  },
  "倒持手板":{
    "category":"慌",
    "related_category":null,
    "word_class":"idiom",
    "emotion_intense":5,
    "total_meanings":1,
    "word_polarity":0
  },
  "楞手楞脚":{
    "category":"贬责",
    "related_category":null,
    "word_class":"idiom",
    "emotion_intense":3,
    "total_meanings":1,
    "word_polarity":2
  },
  "蹊田夺牛":{
    "category":"贬责",
    "related_category":null,
    "word_class":"idiom",
    "emotion_intense":7,
    "total_meanings":3,
    "word_polarity":2
  },
  "蛀齿":{
    "category":"烦闷",
    "related_category":null,
    "word_class":"noun",
    "emotion_intense":6,
    "total_meanings":1,
    "word_polarity":2
  },
  "朱脣粉面":{
    "category":"喜爱",
    "related_category":null,
    "word_class":"idiom",
    "emotion_intense":5,
    "total_meanings":1,
    "word_polarity":1
  },
  "建功立业":{
    "category":"赞扬",
    "related_category":null,
    "word_class":"idiom",
    "emotion_intense":5,
    "total_meanings":1,
    "word_polarity":1
  },
  "不堪其忧":{
    "category":"悲伤",
    "related_category":null,
    "word_class":"idiom",
    "emotion_intense":7,
    "total_meanings":1,
    "word_polarity":2
  },
  "黑不溜秋":{
    "category":"憎恶",
    "related_category":null,
    "word_class":"adj",
    "emotion_intense":3,
    "total_meanings":1,
    "word_polarity":2
  },
  "平衍":{
    "category":"喜爱",
    "related_category":null,
    "word_class":"adj",
    "emotion_intense":6,
    "total_meanings":1,
    "word_polarity":1
  },
  "鹘仑吞枣":{
    "category":"贬责",
    "related_category":null,
    "word_class":"idiom",
    "emotion_intense":5,
    "total_meanings":1,
    "word_polarity":2
  },
  "鬼哭狼嗥":{
    "category":"恐惧",
    "related_category":null,
    "word_class":"idiom",
    "emotion_intense":9,
    "total_meanings":2,
    "word_polarity":2
  },
  "伪君子":{
    "category":"憎恶",
    "related_category":null,
    "word_class":"noun",
    "emotion_intense":7,
    "total_meanings":1,
    "word_polarity":2
  },
  "无可比象":{
    "category":"赞扬",
    "related_category":null,
    "word_class":"idiom",
    "emotion_intense":9,
    "total_meanings":1,
    "word_polarity":1
  },
  "死诸葛能走生仲达":{
    "category":"赞扬",
    "related_category":null,
    "word_class":"idiom",
    "emotion_intense":5,
    "total_meanings":1,
    "word_polarity":1
  },
  "桀黠":{
    "category":"贬责",
    "related_category":null,
    "word_class":"adj",
    "emotion_intense":7,
    "total_meanings":1,
    "word_polarity":2
  },
  "张公吃酒李公颠":{
    "category":"赞扬",
    "related_category":null,
    "word_class":"idiom",
    "emotion_intense":5,
    "total_meanings":1,
    "word_polarity":1
  },
  "水来土掩":{
    "category":"安心",
    "related_category":null,
    "word_class":"idiom",
    "emotion_intense":5,
    "total_meanings":1,
    "word_polarity":1
  },
  "鸿轩凤翥":{
    "category":"相信",
    "related_category":null,
    "word_class":"idiom",
    "emotion_intense":7,
    "total_meanings":1,
    "word_polarity":1
  },
  "好好先生":{
    "category":"贬责",
    "related_category":null,
    "word_class":"noun",
    "emotion_intense":3,
    "total_meanings":1,
    "word_polarity":2
  },
  "文弛武玩":{
    "category":"贬责",
    "related_category":null,
    "word_class":"idiom",
    "emotion_intense":7,
    "total_meanings":1,
    "word_polarity":1
  },
  "伈伈睍睍":{
    "category":"恐惧",
    "related_category":null,
    "word_class":"idiom",
    "emotion_intense":8,
    "total_meanings":1,
    "word_polarity":2
  },
  "野鹤闲云":{
    "category":"快乐",
    "related_category":null,
    "word_class":"idiom",
    "emotion_intense":7,
    "total_meanings":1,
    "word_polarity":1
  },
  "仍旧":{
    "category":"赞扬",
    "related_category":null,
    "word_class":"verb",
    "emotion_intense":5,
    "total_meanings":2,
    "word_polarity":0
  },
  "捕影系风":{
    "category":"怀疑",
    "related_category":null,
    "word_class":"idiom",
    "emotion_intense":5,
    "total_meanings":1,
    "word_polarity":2
  },
  "风行电照":{
    "category":"赞扬",
    "related_category":null,
    "word_class":"idiom",
    "emotion_intense":7,
    "total_meanings":1,
    "word_polarity":1
  },
  "盛装":{
    "category":"赞扬",
    "related_category":null,
    "word_class":"noun",
    "emotion_intense":5,
    "total_meanings":1,
    "word_polarity":1
  },
  "有口无行":{
    "category":"贬责",
    "related_category":null,
    "word_class":"idiom",
    "emotion_intense":5,
    "total_meanings":1,
    "word_polarity":2
  },
  "驷马轩车":{
    "category":"赞扬",
    "related_category":"贬责",
    "word_class":"idiom",
    "emotion_intense":7,
    "total_meanings":1,
    "word_polarity":3
  },
  "黔驴技孤":{
    "category":"贬责",
    "related_category":null,
    "word_class":"idiom",
    "emotion_intense":5,
    "total_meanings":1,
    "word_polarity":2
  },
  "凑巧":{
    "category":"喜爱",
    "related_category":null,
    "word_class":"adj",
    "emotion_intense":3,
    "total_meanings":1,
    "word_polarity":0
  },
  "殒灭":{
    "category":"悲伤",
    "related_category":null,
    "word_class":"verb",
    "emotion_intense":7,
    "total_meanings":1,
    "word_polarity":0
  },
  "雨零星散":{
    "category":"失望",
    "related_category":"悲伤",
    "word_class":"idiom",
    "emotion_intense":5,
    "total_meanings":1,
    "word_polarity":0
  },
  "深见远虑":{
    "category":"赞扬",
    "related_category":null,
    "word_class":"idiom",
    "emotion_intense":5,
    "total_meanings":1,
    "word_polarity":1
  },
  "连枝分叶":{
    "category":"赞扬",
    "related_category":null,
    "word_class":"idiom",
    "emotion_intense":5,
    "total_meanings":1,
    "word_polarity":1
  },
  "金貂取酒":{
    "category":"赞扬",
    "related_category":null,
    "word_class":"idiom",
    "emotion_intense":5,
    "total_meanings":1,
    "word_polarity":1
  },
  "浊骨凡胎":{
    "category":"贬责",
    "related_category":null,
    "word_class":"idiom",
    "emotion_intense":3,
    "total_meanings":1,
    "word_polarity":0
  },
  "谈吐风生":{
    "category":"赞扬",
    "related_category":null,
    "word_class":"idiom",
    "emotion_intense":3,
    "total_meanings":1,
    "word_polarity":1
  },
  "分劳赴功":{
    "category":"赞扬",
    "related_category":null,
    "word_class":"idiom",
    "emotion_intense":5,
    "total_meanings":1,
    "word_polarity":1
  },
  "日新月盛":{
    "category":"赞扬",
    "related_category":null,
    "word_class":"idiom",
    "emotion_intense":7,
    "total_meanings":1,
    "word_polarity":1
  },
  "乐极则忧":{
    "category":"悲伤",
    "related_category":null,
    "word_class":"idiom",
    "emotion_intense":5,
    "total_meanings":1,
    "word_polarity":0
  },
  "嘻皮笑脸":{
    "category":"贬责",
    "related_category":null,
    "word_class":"idiom",
    "emotion_intense":7,
    "total_meanings":3,
    "word_polarity":2
  },
  "英魂":{
    "category":"尊敬",
    "related_category":"赞扬",
    "word_class":"noun",
    "emotion_intense":7,
    "total_meanings":2,
    "word_polarity":1
  },
  "白蜡明经":{
    "category":"失望",
    "related_category":"烦闷",
    "word_class":"idiom",
    "emotion_intense":5,
    "total_meanings":1,
    "word_polarity":0
  },
  "孜孜汲汲":{
    "category":"赞扬",
    "related_category":null,
    "word_class":"idiom",
    "emotion_intense":5,
    "total_meanings":1,
    "word_polarity":1
  },
  "金玉锦绣":{
    "category":"赞扬",
    "related_category":null,
    "word_class":"idiom",
    "emotion_intense":5,
    "total_meanings":1,
    "word_polarity":1
  },
  "保藏":{
    "category":"喜爱",
    "related_category":null,
    "word_class":"verb",
    "emotion_intense":5,
    "total_meanings":1,
    "word_polarity":0
  },
  "绝艺":{
    "category":"赞扬",
    "related_category":null,
    "word_class":"noun",
    "emotion_intense":5,
    "total_meanings":1,
    "word_polarity":1
  },
  "望尘靡及":{
    "category":"失望",
    "related_category":null,
    "word_class":"idiom",
    "emotion_intense":7,
    "total_meanings":1,
    "word_polarity":2
  },
  "適逢其会":{
    "category":"快乐",
    "related_category":null,
    "word_class":"idiom",
    "emotion_intense":5,
    "total_meanings":1,
    "word_polarity":1
  },
  "戒惧":{
    "category":"恐惧",
    "related_category":null,
    "word_class":"verb",
    "emotion_intense":7,
    "total_meanings":1,
    "word_polarity":0
  },
  "正正经经":{
    "category":"赞扬",
    "related_category":null,
    "word_class":"idiom",
    "emotion_intense":5,
    "total_meanings":2,
    "word_polarity":1
  },
  "鸿断鱼沈":{
    "category":"思",
    "related_category":null,
    "word_class":"idiom",
    "emotion_intense":5,
    "total_meanings":1,
    "word_polarity":1
  },
  "鸡肋":{
    "category":"贬责",
    "related_category":null,
    "word_class":"noun",
    "emotion_intense":5,
    "total_meanings":1,
    "word_polarity":2
  },
  "颜精柳骨":{
    "category":"赞扬",
    "related_category":null,
    "word_class":"idiom",
    "emotion_intense":9,
    "total_meanings":1,
    "word_polarity":1
  },
  "人物":{
    "category":"赞扬",
    "related_category":null,
    "word_class":"noun",
    "emotion_intense":7,
    "total_meanings":3,
    "word_polarity":1
  },
  "惨无天日":{
    "category":"憎恶",
    "related_category":null,
    "word_class":"idiom",
    "emotion_intense":9,
    "total_meanings":1,
    "word_polarity":2
  },
  "弓影杯蛇":{
    "category":"怀疑",
    "related_category":null,
    "word_class":"idiom",
    "emotion_intense":5,
    "total_meanings":1,
    "word_polarity":2
  },
  "漫无目标":{
    "category":"贬责",
    "related_category":"烦闷",
    "word_class":"idiom",
    "emotion_intense":5,
    "total_meanings":1,
    "word_polarity":2
  },
  "鱼跃鸢飞":{
    "category":"喜爱",
    "related_category":null,
    "word_class":"idiom",
    "emotion_intense":7,
    "total_meanings":1,
    "word_polarity":1
  },
  "通忧共患":{
    "category":"赞扬",
    "related_category":null,
    "word_class":"idiom",
    "emotion_intense":7,
    "total_meanings":1,
    "word_polarity":1
  },
  "曲意承迎":{
    "category":"贬责",
    "related_category":null,
    "word_class":"idiom",
    "emotion_intense":5,
    "total_meanings":1,
    "word_polarity":2
  },
  "狎妓":{
    "category":"憎恶",
    "related_category":null,
    "word_class":"verb",
    "emotion_intense":3,
    "total_meanings":1,
    "word_polarity":2
  },
  "流天澈地":{
    "category":"憎恶",
    "related_category":null,
    "word_class":"idiom",
    "emotion_intense":1,
    "total_meanings":1,
    "word_polarity":2
  },
  "江郎才掩":{
    "category":"贬责",
    "related_category":null,
    "word_class":"idiom",
    "emotion_intense":5,
    "total_meanings":1,
    "word_polarity":2
  },
  "斗霜傲雪":{
    "category":"赞扬",
    "related_category":null,
    "word_class":"idiom",
    "emotion_intense":7,
    "total_meanings":1,
    "word_polarity":1
  },
  "摧枯折腐":{
    "category":"赞扬",
    "related_category":null,
    "word_class":"idiom",
    "emotion_intense":7,
    "total_meanings":1,
    "word_polarity":1
  },
  "览闻辩见":{
    "category":"赞扬",
    "related_category":null,
    "word_class":"adj",
    "emotion_intense":7,
    "total_meanings":1,
    "word_polarity":1
  },
  "显山露水":{
    "category":"赞扬",
    "related_category":null,
    "word_class":"idiom",
    "emotion_intense":5,
    "total_meanings":1,
    "word_polarity":1
  },
  "虎尾春冰":{
    "category":"恐惧",
    "related_category":null,
    "word_class":"idiom",
    "emotion_intense":7,
    "total_meanings":1,
    "word_polarity":2
  },
  "抱头大哭":{
    "category":"悲伤",
    "related_category":null,
    "word_class":"idiom",
    "emotion_intense":5,
    "total_meanings":1,
    "word_polarity":0
  },
  "坐树不言":{
    "category":"安心",
    "related_category":null,
    "word_class":"idiom",
    "emotion_intense":7,
    "total_meanings":1,
    "word_polarity":1
  },
  "令行禁止":{
    "category":"赞扬",
    "related_category":null,
    "word_class":"idiom",
    "emotion_intense":7,
    "total_meanings":1,
    "word_polarity":1
  },
  "观眉说眼":{
    "category":"憎恶",
    "related_category":null,
    "word_class":"idiom",
    "emotion_intense":5,
    "total_meanings":1,
    "word_polarity":2
  },
  "运斤如风":{
    "category":"赞扬",
    "related_category":null,
    "word_class":"idiom",
    "emotion_intense":5,
    "total_meanings":1,
    "word_polarity":1
  },
  "未为不可":{
    "category":"赞扬",
    "related_category":null,
    "word_class":"idiom",
    "emotion_intense":5,
    "total_meanings":1,
    "word_polarity":1
  },
  "十转九空":{
    "category":"贬责",
    "related_category":null,
    "word_class":"idiom",
    "emotion_intense":5,
    "total_meanings":1,
    "word_polarity":2
  },
  "金榜":{
    "category":"赞扬",
    "related_category":null,
    "word_class":"noun",
    "emotion_intense":9,
    "total_meanings":1,
    "word_polarity":1
  },
  "横眉冷眼":{
    "category":"愤怒",
    "related_category":null,
    "word_class":"idiom",
    "emotion_intense":9,
    "total_meanings":1,
    "word_polarity":2
  },
  "尖言冷语":{
    "category":"贬责",
    "related_category":null,
    "word_class":"idiom",
    "emotion_intense":5,
    "total_meanings":1,
    "word_polarity":2
  },
  "忧国奉公":{
    "category":"赞扬",
    "related_category":null,
    "word_class":"idiom",
    "emotion_intense":9,
    "total_meanings":1,
    "word_polarity":1
  },
  "老生常谈":{
    "category":"贬责",
    "related_category":null,
    "word_class":"idiom",
    "emotion_intense":7,
    "total_meanings":1,
    "word_polarity":2
  },
  "凤凰来仪":{
    "category":"快乐",
    "related_category":null,
    "word_class":"idiom",
    "emotion_intense":5,
    "total_meanings":1,
    "word_polarity":1
  },
  "泥猪疥狗":{
    "category":"贬责",
    "related_category":null,
    "word_class":"idiom",
    "emotion_intense":5,
    "total_meanings":1,
    "word_polarity":2
  },
  "松柏寒盟":{
    "category":"赞扬",
    "related_category":null,
    "word_class":"idiom",
    "emotion_intense":9,
    "total_meanings":1,
    "word_polarity":1
  },
  "上窜下跳":{
    "category":"贬责",
    "related_category":null,
    "word_class":"idiom",
    "emotion_intense":5,
    "total_meanings":1,
    "word_polarity":2
  },
  "离世异俗":{
    "category":"赞扬",
    "related_category":null,
    "word_class":"idiom",
    "emotion_intense":7,
    "total_meanings":1,
    "word_polarity":1
  },
  "追根查源":{
    "category":"怀疑",
    "related_category":null,
    "word_class":"idiom",
    "emotion_intense":5,
    "total_meanings":1,
    "word_polarity":0
  },
  "喧腾":{
    "category":"快乐",
    "related_category":null,
    "word_class":"verb",
    "emotion_intense":7,
    "total_meanings":2,
    "word_polarity":0
  },
  "枭心鹤貌":{
    "category":"贬责",
    "related_category":null,
    "word_class":"idiom",
    "emotion_intense":5,
    "total_meanings":1,
    "word_polarity":2
  },
  "维妙维肖":{
    "category":"赞扬",
    "related_category":null,
    "word_class":"idiom",
    "emotion_intense":7,
    "total_meanings":1,
    "word_polarity":1
  },
  "陂湖禀量":{
    "category":"赞扬",
    "related_category":null,
    "word_class":"idiom",
    "emotion_intense":5,
    "total_meanings":1,
    "word_polarity":1
  },
  "静若处子，动若脱兔":{
    "category":"赞扬",
    "related_category":null,
    "word_class":"idiom",
    "emotion_intense":5,
    "total_meanings":1,
    "word_polarity":1
  },
  "袍哥":{
    "category":"贬责",
    "related_category":null,
    "word_class":"noun",
    "emotion_intense":3,
    "total_meanings":1,
    "word_polarity":2
  },
  "歪不横楞":{
    "category":"贬责",
    "related_category":null,
    "word_class":"idiom",
    "emotion_intense":7,
    "total_meanings":1,
    "word_polarity":2
  },
  "手疾眼快":{
    "category":"赞扬",
    "related_category":null,
    "word_class":"idiom",
    "emotion_intense":5,
    "total_meanings":1,
    "word_polarity":1
  },
  "才誇八斗":{
    "category":"赞扬",
    "related_category":null,
    "word_class":"idiom",
    "emotion_intense":5,
    "total_meanings":1,
    "word_polarity":1
  },
  "驾鹤成仙":{
    "category":"悲伤",
    "related_category":null,
    "word_class":"idiom",
    "emotion_intense":7,
    "total_meanings":1,
    "word_polarity":0
  },
  "荣誉军人":{
    "category":"尊敬",
    "related_category":null,
    "word_class":"noun",
    "emotion_intense":7,
    "total_meanings":1,
    "word_polarity":1
  },
  "牙签犀轴":{
    "category":"赞扬",
    "related_category":null,
    "word_class":"idiom",
    "emotion_intense":7,
    "total_meanings":1,
    "word_polarity":1
  },
  "圣上":{
    "category":"尊敬",
    "related_category":null,
    "word_class":"noun",
    "emotion_intense":5,
    "total_meanings":1,
    "word_polarity":1
  },
  "弃甲投戈":{
    "category":"贬责",
    "related_category":null,
    "word_class":"idiom",
    "emotion_intense":3,
    "total_meanings":1,
    "word_polarity":2
  },
  "残喘":{
    "category":"悲伤",
    "related_category":null,
    "word_class":"verb",
    "emotion_intense":5,
    "total_meanings":1,
    "word_polarity":2
  },
  "身名俱败":{
    "category":"悲伤",
    "related_category":null,
    "word_class":"idiom",
    "emotion_intense":7,
    "total_meanings":1,
    "word_polarity":2
  },
  "铜浇铁铸":{
    "category":"赞扬",
    "related_category":null,
    "word_class":"idiom",
    "emotion_intense":7,
    "total_meanings":1,
    "word_polarity":1
  },
  "嫌长道短":{
    "category":"贬责",
    "related_category":null,
    "word_class":"idiom",
    "emotion_intense":5,
    "total_meanings":1,
    "word_polarity":2
  },
  "搬脣递舌":{
    "category":"贬责",
    "related_category":null,
    "word_class":"idiom",
    "emotion_intense":7,
    "total_meanings":1,
    "word_polarity":2
  },
  "欢呼鼓舞":{
    "category":"快乐",
    "related_category":null,
    "word_class":"idiom",
    "emotion_intense":7,
    "total_meanings":1,
    "word_polarity":0
  },
  "寒腹短识":{
    "category":"贬责",
    "related_category":null,
    "word_class":"idiom",
    "emotion_intense":7,
    "total_meanings":1,
    "word_polarity":2
  },
  "噱头":{
    "category":"快乐",
    "related_category":null,
    "word_class":"noun",
    "emotion_intense":7,
    "total_meanings":1,
    "word_polarity":1
  },
  "死有余诛":{
    "category":"贬责",
    "related_category":null,
    "word_class":"idiom",
    "emotion_intense":7,
    "total_meanings":1,
    "word_polarity":2
  },
  "事迹":{
    "category":"赞扬",
    "related_category":null,
    "word_class":"noun",
    "emotion_intense":7,
    "total_meanings":1,
    "word_polarity":1
  },
  "无有伦比":{
    "category":"赞扬",
    "related_category":null,
    "word_class":"idiom",
    "emotion_intense":9,
    "total_meanings":1,
    "word_polarity":1
  },
  "橡皮图章":{
    "category":"贬责",
    "related_category":null,
    "word_class":"noun",
    "emotion_intense":5,
    "total_meanings":2,
    "word_polarity":2
  },
  "倒持干戈":{
    "category":"贬责",
    "related_category":null,
    "word_class":"idiom",
    "emotion_intense":5,
    "total_meanings":1,
    "word_polarity":2
  },
  "鸾飘凤泊":{
    "category":"赞扬",
    "related_category":null,
    "word_class":"idiom",
    "emotion_intense":7,
    "total_meanings":1,
    "word_polarity":1
  },
  "雕虫刻篆":{
    "category":"贬责",
    "related_category":null,
    "word_class":"idiom",
    "emotion_intense":5,
    "total_meanings":1,
    "word_polarity":2
  },
  "流离颠沛":{
    "category":"悲伤",
    "related_category":null,
    "word_class":"idiom",
    "emotion_intense":9,
    "total_meanings":1,
    "word_polarity":2
  },
  "闺英闱秀":{
    "category":"赞扬",
    "related_category":null,
    "word_class":"idiom",
    "emotion_intense":5,
    "total_meanings":1,
    "word_polarity":1
  },
  "鸡鸣狗吠":{
    "category":"憎恶",
    "related_category":null,
    "word_class":"idiom",
    "emotion_intense":9,
    "total_meanings":1,
    "word_polarity":2
  },
  "一发破的":{
    "category":"赞扬",
    "related_category":null,
    "word_class":"idiom",
    "emotion_intense":8,
    "total_meanings":1,
    "word_polarity":1
  },
  "变戏法":{
    "category":"喜爱",
    "related_category":null,
    "word_class":"verb",
    "emotion_intense":5,
    "total_meanings":1,
    "word_polarity":1
  },
  "谭天说地":{
    "category":"赞扬",
    "related_category":null,
    "word_class":"idiom",
    "emotion_intense":7,
    "total_meanings":1,
    "word_polarity":1
  }
}